Workbook
Name Category: #REF!
Name Customer: 'Customer Info'!$A$1:$I$501
Name Customer_Head: 'Customer Info'!$A$1:$I$1
Name Product: #REF!
Name Product_Head: #REF!
Name Product_ID: #REF!
Name Product_Name: #REF!
Name Sub_Category: #REF!

Sheet Sales Order 
T1: Amount | U1: Commission %
T2: 0 | U2: 0.02
T3: 5000 | U3: 0.05
T4: 25000 | U4: 0.07
T5: 50000 | U5: 0.09
T6: 100000 | U6: 0.12
G7: By Using VLookUp Find all the First Name , Last Name and City from another Customer Info Sheet | M7: Cost* Quantity | N7: Price * Quantity | P7: Total Sales+ Shipping Cost | Q7: Total Sales- Total Cost | S7: By using above small table | T7: 250000 | U7: 0.15
S8: Calculate Commision Based on Amt
A9: Order ID | B9: Order Date | C9: Ship Date | D9: Product Category | E9: Order_Source | F9: Customer_ID | G9: Customer First Name | H9: Customer Last Name | I9: City | J9: Price | K9: Cost | L9: Quantity | M9: Total_Cost | N9: Tota_Sales | O9: Shiping Cost | P9: Tot_Sales_Amt | Q9: Profit | R9: Order Priority | S9: Sales Person Commission
A10: AU-2018-10553 | B10: 43458 | C10: 43458 | D10: Furniture | E10: Flipkart | F10: CS-04692 | G10: =VLOOKUP(F10,'Customer Info'!A:B,2,FALSE) -> Cari | H10: =VLOOKUP(F10,'Customer Info'!A:C,3,FALSE) -> Sayre | I10: =VLOOKUP(F10,'Customer Info'!A:E,4,FALSE) -> Corporate | J10: 1834 | K10: 1716 | L10: 2 | M10: =K10*L10 -> 3432 | N10: =J10*L10 -> 3668 | O10: 53 | P10: =N10+O10 -> 3721 | Q10: =N10-M10 -> 236 | R10: Critical | S10: {=_xlfn.IFS(P10<5000, P10*2%, P10<25000, P10*5%, P10<50000, P10*7%, P10<10000, P10*9%, P10<250000, P10*12%, P10>=250000, P10*15%)} -> 74.42
A11: AU-2018-10651 | B11: 43304 | C11: 43306 | D11: Furniture | E11: Flipkart | F11: MG-21584 | G11: =VLOOKUP(F11,'Customer Info'!A:B,2,FALSE) -> Michael | H11: =VLOOKUP(F11,'Customer Info'!A:C,3,FALSE) -> Granlund | I11: =VLOOKUP(F11,'Customer Info'!A:E,4,FALSE) -> Home Office | J11: 4798 | K11: 4448 | L11: 6 | M11: =K11*L11 -> 26688 | N11: =J11*L11 -> 28788 | O11: 91 | P11: =N11+O11 -> 28879 | Q11: =N11-M11 -> 2100 | R11: Medium | S11: {=_xlfn.IFS(P11<5000, P11*2%, P11<25000, P11*5%, P11<50000, P11*7%, P11<10000, P11*9%, P11<250000, P11*12%, P11>=250000, P11*15%)} -> 2021.53
A12: AU-2018-10857 | B12: 43397 | C12: 43399 | D12: Technology | E12: Amazon | F12: ML-21811 | G12: =VLOOKUP(F12,'Customer Info'!A:B,2,FALSE) -> Muhammed | H12: =VLOOKUP(F12,'Customer Info'!A:C,3,FALSE) -> Lee | I12: =VLOOKUP(F12,'Customer Info'!A:E,4,FALSE) -> Consumer | J12: 2808 | K12: 2674 | L12: 3 | M12: =K12*L12 -> 8022 | N12: =J12*L12 -> 8424 | O12: 47 | P12: =N12+O12 -> 8471 | Q12: =N12-M12 -> 402 | R12: Medium | S12: {=_xlfn.IFS(P12<5000, P12*2%, P12<25000, P12*5%, P12<50000, P12*7%, P12<10000, P12*9%, P12<250000, P12*12%, P12>=250000, P12*15%)} -> 423.55
A13: AU-2018-10892 | B13: 43147 | C13: 43148 | D13: Furniture | E13: Flipkart | F13: RD-27712 | G13: =VLOOKUP(F13,'Customer Info'!A:B,2,FALSE) -> Rick | H13: =VLOOKUP(F13,'Customer Info'!A:C,3,FALSE) -> Duston | I13: =VLOOKUP(F13,'Customer Info'!A:E,4,FALSE) -> Corporate | J13: 1816 | K13: 1699 | L13: 2 | M13: =K13*L13 -> 3398 | N13: =J13*L13 -> 3632 | O13: 73 | P13: =N13+O13 -> 3705 | Q13: =N13-M13 -> 234 | R13: Medium | S13: {=_xlfn.IFS(P13<5000, P13*2%, P13<25000, P13*5%, P13<50000, P13*7%, P13<10000, P13*9%, P13<250000, P13*12%, P13>=250000, P13*15%)} -> 74.1
A14: AU-2018-11021 | B14: 43369 | C14: 43371 | D14: Technology | E14: Snapdeal | F14: SN-28948 | G14: =VLOOKUP(F14,'Customer Info'!A:B,2,FALSE) -> Steve | H14: =VLOOKUP(F14,'Customer Info'!A:C,3,FALSE) -> Nguyen | I14: =VLOOKUP(F14,'Customer Info'!A:E,4,FALSE) -> Consumer | J14: 1668 | K14: 1636 | L14: 4 | M14: =K14*L14 -> 6544 | N14: =J14*L14 -> 6672 | O14: 66 | P14: =N14+O14 -> 6738 | Q14: =N14-M14 -> 128 | R14: Medium | S14: {=_xlfn.IFS(P14<5000, P14*2%, P14<25000, P14*5%, P14<50000, P14*7%, P14<10000, P14*9%, P14<250000, P14*12%, P14>=250000, P14*15%)} -> 336.9
A15: AU-2018-11055 | B15: 43295 | C15: 43296 | D15: Office Supplies | E15: India_Mart | F15: MM-22019 | G15: =VLOOKUP(F15,'Customer Info'!A:B,2,FALSE) -> Michael | H15: =VLOOKUP(F15,'Customer Info'!A:C,3,FALSE) -> Moore | I15: =VLOOKUP(F15,'Customer Info'!A:E,4,FALSE) -> Consumer | J15: 97 | K15: 92 | L15: 6 | M15: =K15*L15 -> 552 | N15: =J15*L15 -> 582 | O15: 10 | P15: =N15+O15 -> 592 | Q15: =N15-M15 -> 30 | R15: Medium | S15: {=_xlfn.IFS(P15<5000, P15*2%, P15<25000, P15*5%, P15<50000, P15*7%, P15<10000, P15*9%, P15<250000, P15*12%, P15>=250000, P15*15%)} -> 11.84
A16: AU-2018-11228 | B16: 43132 | C16: 43132 | D16: Furniture | E16: Amazon | F16: JO-16901 | G16: =VLOOKUP(F16,'Customer Info'!A:B,2,FALSE) -> Jas | H16: =VLOOKUP(F16,'Customer Info'!A:C,3,FALSE) -> O'Carroll | I16: =VLOOKUP(F16,'Customer Info'!A:E,4,FALSE) -> Corporate | J16: 2790 | K16: 2557 | L16: 2 | M16: =K16*L16 -> 5114 | N16: =J16*L16 -> 5580 | O16: 98 | P16: =N16+O16 -> 5678 | Q16: =N16-M16 -> 466 | R16: Medium | S16: {=_xlfn.IFS(P16<5000, P16*2%, P16<25000, P16*5%, P16<50000, P16*7%, P16<10000, P16*9%, P16<250000, P16*12%, P16>=250000, P16*15%)} -> 283.9
A17: AU-2018-11473 | B17: 43256 | C17: 43258 | D17: Office Supplies | E17: Amazon | F17: CS-08000 | G17: =VLOOKUP(F17,'Customer Info'!A:B,2,FALSE) -> Cindy | H17: =VLOOKUP(F17,'Customer Info'!A:C,3,FALSE) -> Schnelling | I17: =VLOOKUP(F17,'Customer Info'!A:E,4,FALSE) -> Corporate | J17: 138 | K17: 128 | L17: 3 | M17: =K17*L17 -> 384 | N17: =J17*L17 -> 414 | O17: 30 | P17: =N17+O17 -> 444 | Q17: =N17-M17 -> 30 | R17: Medium | S17: {=_xlfn.IFS(P17<5000, P17*2%, P17<25000, P17*5%, P17<50000, P17*7%, P17<10000, P17*9%, P17<250000, P17*12%, P17>=250000, P17*15%)} -> 8.88
A18: AU-2018-11635 | B18: 43315 | C18: 43315 | D18: Office Supplies | E18: Snapdeal | F18: JE-16318 | G18: =VLOOKUP(F18,'Customer Info'!A:B,2,FALSE) -> Jeremy | H18: =VLOOKUP(F18,'Customer Info'!A:C,3,FALSE) -> Ellison | I18: =VLOOKUP(F18,'Customer Info'!A:E,4,FALSE) -> Corporate | J18: 162 | K18: 148 | L18: 3 | M18: =K18*L18 -> 444 | N18: =J18*L18 -> 486 | O18: 30 | P18: =N18+O18 -> 516 | Q18: =N18-M18 -> 42 | R18: Medium | S18: {=_xlfn.IFS(P18<5000, P18*2%, P18<25000, P18*5%, P18<50000, P18*7%, P18<10000, P18*9%, P18<250000, P18*12%, P18>=250000, P18*15%)} -> 10.32
A19: AU-2018-11675 | B19: 43262 | C19: 43264 | D19: Furniture | E19: Snapdeal | F19: CM-06731 | G19: =VLOOKUP(F19,'Customer Info'!A:B,2,FALSE) -> Corinna | H19: =VLOOKUP(F19,'Customer Info'!A:C,3,FALSE) -> Mitchell | I19: =VLOOKUP(F19,'Customer Info'!A:E,4,FALSE) -> Consumer | J19: 1637 | K19: 1591 | L19: 1 | M19: =K19*L19 -> 1591 | N19: =J19*L19 -> 1637 | O19: 57 | P19: =N19+O19 -> 1694 | Q19: =N19-M19 -> 46 | R19: High | S19: {=_xlfn.IFS(P19<5000, P19*2%, P19<25000, P19*5%, P19<50000, P19*7%, P19<10000, P19*9%, P19<250000, P19*12%, P19>=250000, P19*15%)} -> 33.88
A20: AU-2018-11700 | B20: 43280 | C20: 43280 | D20: Furniture | E20: Snapdeal | F20: VP-33803 | G20: =VLOOKUP(F20,'Customer Info'!A:B,2,FALSE) -> Victor | H20: =VLOOKUP(F20,'Customer Info'!A:C,3,FALSE) -> Preis | I20: =VLOOKUP(F20,'Customer Info'!A:E,4,FALSE) -> Home Office | J20: 1364 | K20: 1274 | L20: 2 | M20: =K20*L20 -> 2548 | N20: =J20*L20 -> 2728 | O20: 56 | P20: =N20+O20 -> 2784 | Q20: =N20-M20 -> 180 | R20: Medium | S20: {=_xlfn.IFS(P20<5000, P20*2%, P20<25000, P20*5%, P20<50000, P20*7%, P20<10000, P20*9%, P20<250000, P20*12%, P20>=250000, P20*15%)} -> 55.68
A21: AU-2018-11960 | B21: 43173 | C21: 43175 | D21: Office Supplies | E21: Referral | F21: JC-15796 | G21: =VLOOKUP(F21,'Customer Info'!A:B,2,FALSE) -> Jenna | H21: =VLOOKUP(F21,'Customer Info'!A:C,3,FALSE) -> Caffey | I21: =VLOOKUP(F21,'Customer Info'!A:E,4,FALSE) -> Consumer | J21: 169 | K21: 160 | L21: 2 | M21: =K21*L21 -> 320 | N21: =J21*L21 -> 338 | O21: 30 | P21: =N21+O21 -> 368 | Q21: =N21-M21 -> 18 | R21: Low | S21: {=_xlfn.IFS(P21<5000, P21*2%, P21<25000, P21*5%, P21<50000, P21*7%, P21<10000, P21*9%, P21<250000, P21*12%, P21>=250000, P21*15%)} -> 7.36
... A4815: IN-2020-99568 | B4815: 43994 | C4815: 43996 | D4815: Office Supplies | E4815: India_Mart | F4815: AO-01810 | G4815: =VLOOKUP(F4815,'Customer Info'!A:B,2,FALSE) -> Anthony | H4815: =VLOOKUP(F4815,'Customer Info'!A:C,3,FALSE) -> O'Donnell | I4815: =VLOOKUP(F4815,'Customer Info'!A:E,4,FALSE) -> Corporate | J4815: 851 | K4815: 773 | L4815: 2 | M4815: =K4815*L4815 -> 1546 | N4815: =J4815*L4815 -> 1702 | O4815: 98 | P4815: =N4815+O4815 -> 1800 | Q4815: =N4815-M4815 -> 156 | R4815: Critical | S4815: {=_xlfn.IFS(P4815<5000, P4815*2%, P4815<25000, P4815*5%, P4815<50000, P4815*7%, P4815<10000, P4815*9%, P4815<250000, P4815*12%, P4815>=250000, P4815*15%)} -> 36

Sheet Customer Info
A1: Customer ID | B1: Customer First Name | C1: Customer Last Name | D1: Segment | E1: City | F1: State | G1: Country | H1: Region | I1: Age
A2: AB-00014 | B2: Aaron | C2: Bergman | D2: Corporate | E2: Halle | F2: SaxonyAnhalt | G2: Germany | H2: Central | I2: 57
A3: AS-00460 | B3: Aaron | C3: Smayling | D3: Corporate | E3: Dresden | F3: Saxony | G3: Germany | H3: Central | I3: 61
A4: AS-00312 | B4: Aaron | C4: Smayling | D4: Home Office | E4: Port Macquarie | F4: New South Wales | G4: Australia | H4: Oceania | I4: 72
A5: AH-00052 | B5: Aaron | C5: Hawkins | D5: Consumer | E5: Minden | F5: North RhineWestphalia | G5: Germany | H5: Central | I5: 72
A6: AB-01482 | B6: Adam | C6: Bellavance | D6: Corporate | E6: Kwinana | F6: Western Australia | G6: Australia | H6: Oceania | I6: 57 | K6: Enter First Name | L6: Aaron
A7: AB-01343 | B7: Adam | C7: Bellavance | D7: Corporate | E7: Kaiyuan | F7: Liaoning | G7: China | H7: North Asia | I7: 79 | K7: Enter Last Name | L7: Hawkins
A8: AB-01473 | B8: Adam | C8: Bellavance | D8: Consumer | E8: Medan | F8: Sumatera Utara | G8: Indonesia | H8: Southeast Asia | I8: 64 | K8: City | L8: {=INDEX(E1:E501,MATCH(L6&L7,B1:B501&C1:C501,0))} -> Minden
A9: AB-01525 | B9: Adrian | C9: Barton | D9: Corporate | E9: Wetzlar | F9: Hesse | G9: Germany | H9: Central | I9: 78
A10: AB-01494 | B10: Adrian | C10: Barton | D10: Consumer | E10: Zigong | F10: Sichuan | G10: China | H10: North Asia | I10: 30
A11: AS-01405 | B11: Alan | C11: Shonely | D11: Corporate | E11: Canberra | F11: Australian Capital Territory | G11: Australia | H11: Oceania | I11: 57
A12: AS-01458 | B12: Alan | C12: Schoenberger | D12: Home Office | E12: Anshan | F12: Liaoning | G12: China | H12: North Asia | I12: 40
A13: AB-02405 | B13: Alejandro | C13: Ballentine | D13: Consumer | E13: Mannheim | F13: BadenWŸrttemberg | G13: Germany | H13: Central | I13: 39
A14: AG-02487 | B14: Alejandro | C14: Grove | D14: Consumer | E14: Whyalla | F14: South Australia | G14: Australia | H14: Oceania | I14: 37
A15: AG-00272 | B15: Alex | C15: Grayson | D15: Consumer | E15: Anyang | F15: Henan | G15: China | H15: North Asia | I15: 60
A16: AA-02503 | B16: Alex | C16: Avila | D16: Consumer | E16: Agra | F16: Uttar Pradesh | G16: India | H16: Central Asia | I16: 67
A17: AA-02455 | B17: Alex | C17: Avila | D17: Consumer | E17: Berlin | F17: Berlin | G17: Germany | H17: Central | I17: 42
A18: AA-02321 | B18: Alex | C18: Avila | D18: Corporate | E18: Newcastle | F18: New South Wales | G18: Australia | H18: Oceania | I18: 66
A19: AM-00201 | B19: Alice | C19: McCarthy | D19: Consumer | E19: Berlin | F19: Berlin | G19: Germany | H19: Central | I19: 30
A20: AR-00275 | B20: Allen | C20: Rosenblatt | D20: Consumer | E20: Chaozhou | F20: Guangdong | G20: China | H20: North Asia | I20: 74
... A501: YS-34261 | B501: Yana | C501: Sorensen | D501: Corporate | E501: Bottrop | F501: North RhineWestphalia | G501: Germany | H501: Central | I501: 70
